flow2ml/Data_Augumentation.py
flow2ml/Data_Loader.py
flow2ml/Filters.py
flow2ml/Flow.py
flow2ml/__init__.py
flow2ml_test_2-1.0.2.dist-info/METADATA
flow2ml_test_2-1.0.2.dist-info/WHEEL
flow2ml_test_2-1.0.2.dist-info/top_level.txt
flow2ml_test_2-1.0.2.dist-info/RECORD
