Metadata-Version: 2.1
Name: flow2ml-test-2
Version: 1.0.2
Summary: flow2ml
Home-page: UNKNOWN
Author: UNKNOWN
Author-email: UNKNOWN
License: UNKNOWN
Platform: UNKNOWN
